llama_index/retrievers/vertexai_search/__init__.py
llama_index/retrievers/vertexai_search/_utils.py
llama_index/retrievers/vertexai_search/base.py
llama_index_retrievers_vertexai_search-0.3.1.dist-info/METADATA
llama_index_retrievers_vertexai_search-0.3.1.dist-info/WHEEL
llama_index_retrievers_vertexai_search-0.3.1.dist-info/licenses/LICENSE
llama_index_retrievers_vertexai_search-0.3.1.dist-info/RECORD
