Metadata-Version: 2.4
Name: llama-index-retrievers-vertexai-search
Version: 0.3.1
Summary: llama-index retrievers vertex ai search integration
Author-email: Dave Wang <wangdave@google.com>
License-Expression: MIT
License-File: LICENSE
Requires-Python: <4.0,>=3.9
Requires-Dist: google-auth-httplib2<0.3,>=0.2.0
Requires-Dist: google-auth-oauthlib<2,>=1.2.0
Requires-Dist: google-cloud-aiplatform<2,>=1.53.0
Requires-Dist: google-cloud-discoveryengine<0.12,>=0.11.13
Requires-Dist: llama-index-core<0.15,>=0.13.0
